CHANGES.rst
CONTRIBUTORS.rst
LICENSE.rst
MANIFEST.in
README.rst
setup.py
docs/conf.py
docs/index.md
src/urban/__init__.py
src/urban.events.egg-info/PKG-INFO
src/urban.events.egg-info/SOURCES.txt
src/urban.events.egg-info/dependency_links.txt
src/urban.events.egg-info/entry_points.txt
src/urban.events.egg-info/namespace_packages.txt
src/urban.events.egg-info/not-zip-safe
src/urban.events.egg-info/requires.txt
src/urban.events.egg-info/top_level.txt
src/urban/events/__init__.py
src/urban/events/configure.zcml
src/urban/events/interfaces.py
src/urban/events/migrations.py
src/urban/events/permissions.zcml
src/urban/events/setuphandlers.py
src/urban/events/testing.py
src/urban/events/utils.py
src/urban/events/browser/__init__.py
src/urban/events/browser/configure.zcml
src/urban/events/browser/overrides/.gitkeep
src/urban/events/browser/static/.gitkeep
src/urban/events/locales/README.rst
src/urban/events/locales/__init__.py
src/urban/events/locales/update.py
src/urban/events/locales/update.sh
src/urban/events/locales/urban.events.pot
src/urban/events/locales/en/LC_MESSAGES/urban.events.mo
src/urban/events/locales/en/LC_MESSAGES/urban.events.po
src/urban/events/locales/fr/LC_MESSAGES/urban.events.mo
src/urban/events/locales/fr/LC_MESSAGES/urban.events.po
src/urban/events/profiles/config/liege/codt_article127/codt_article127.json
src/urban/events/profiles/config/liege/codt_buildlicence/codt_buildlicence.json
src/urban/events/profiles/config/liege/codt_parceloutlicence/codt_parceloutlicence.json
src/urban/events/profiles/config/liege/codt_uniquelicence/codt_uniquelicence.json
src/urban/events/profiles/config/liege/codt_urbancertificatetwo/codt_urbancertificatetwo.json
src/urban/events/profiles/config/liege/ticket/ticket.json
src/urban/events/profiles/config/standard/codt_article127/codt_article127.json
src/urban/events/profiles/config/standard/codt_buildlicence/codt_buildlicence.json
src/urban/events/profiles/config/standard/codt_parceloutlicence/codt_parceloutlicence.json
src/urban/events/profiles/config/standard/codt_uniquelicence/codt_uniquelicence.json
src/urban/events/profiles/config/standard/codt_urbancertificatetwo/codt_urbancertificatetwo.json
src/urban/events/profiles/config/standard/ticket/ticket.json
src/urban/events/profiles/default/browserlayer.xml
