Metadata-Version: 2.1
Name: urban.events
Version: 1.0.0a5
Summary: Events configuration for Urban
Home-page: https://github.com/IMIO/urban.events
Author: Affinitic
Author-email: support@imio.be
License: GPL version 2
Project-URL: PyPI, https://pypi.python.org/pypi/urban.events
Project-URL: Source, https://github.com/IMIO/urban.events
Project-URL: Tracker, https://github.com/IMIO/urban.events/issues
Keywords: Python Plone CMS
Platform: UNKNOWN
Classifier: Environment :: Web Environment
Classifier: Framework :: Plone
Classifier: Framework :: Plone :: Addon
Classifier: Framework :: Plone :: 4.3
Classifier: Programming Language :: Python
Classifier: Programming Language :: Python :: 2.7
Classifier: Operating System :: OS Independent
Classifier: License :: OSI Approved :: GNU General Public License v2 (GPLv2)
Requires-Python: ==2.7
Provides-Extra: test
